setup.py
urlmap/__init__.py
urlmap.egg-info/PKG-INFO
urlmap.egg-info/SOURCES.txt
urlmap.egg-info/dependency_links.txt
urlmap.egg-info/top_level.txt