Metadata-Version: 1.0
Name: urlmap
Version: 0.1.0
Summary: Map urls to Python objects
Home-page: https://github.com/0wls/urlmap
Author: Benjamin Sherratt
Author-email: ben.sherratt@gmail.com
License: MIT
Platform: UNKNOWN
